graphgt/__init__.py
graphgt/dataloader.py
graphgt/evaluator.py
graphgt/meta.py
graphgt/utils.py
graphgt/visualizer.py
graphgt-0.1.8.dist-info/METADATA
graphgt-0.1.8.dist-info/RECORD
graphgt-0.1.8.dist-info/WHEEL
graphgt-0.1.8.dist-info/top_level.txt
