Metadata-Version: 2.1
Name: graphgt
Version: 0.1.8
Summary: A Graph Generation and Transformation Dataset Collection
Home-page: https://graphgt.github.io/
Author: Yuanqi Du
Author-email: ydu6@gmu.edu
License: UNKNOWN
Platform: UNKNOWN
Classifier: Intended Audience :: Science/Research
Classifier: Operating System :: POSIX :: Linux
Classifier: Programming Language :: Python :: 3.7
Requires-Dist: numpy
